{
  "server": {
    "port": 3000,
    "youtube-api-key": "",
    "admin-password": "admin"
  },
  "rooms": {
    "default": {
      "maxUsers": 0,
      "secret": {
        "password": ""
      },
      "capture": {
        "mic": {
          "enabled": true,
          "maxBitrate": 128,
          "maxStreams": 24
        },
        "video": {
          "enabled": true,
          "maxBitrate": 4500,
          "maxFramerate": 30,
          "maxWidth": 1280,
          "maxHeight": 720,
          "maxStreams": 3
        },
        "audio": {
          "enabled": true,
          "maxBitrate": 128
        },
        "webcam": {
          "enabled": true,
          "maxBitrate": 2000,
          "maxFramerate": 30,
          "maxWidth": 1280,
          "maxHeight": 720,
          "maxStreams": 9
        },
        "player": {
          "enabled": true,
          "maxStreams": 1
        }
      }
    }
  }
}
